{
    "0": {
        "mjd": 58727.4225694,
        "passband": 1,
        "mag": 20.6471,
        "mag_err": 0.256316,
        "locus_id": "ZTF19abvhkst"
    },
    "1": {
        "mjd": 58727.446296300004,
        "passband": 1,
        "mag": 20.4089,
        "mag_err": 0.23340100000000003,
        "locus_id": "ZTF19abvhkst"
    },
    "2": {
        "mjd": 58727.486296300005,
        "passband": 2,
        "mag": 20.6719,
        "mag_err": 0.240302,
        "locus_id": "ZTF19abvhkst"
    },
    "3": {
        "mjd": 58727.48675930001,
        "passband": 2,
        "mag": 20.5698,
        "mag_err": 0.21053200000000002,
        "locus_id": "ZTF19abvhkst"
    },
    "4": {
        "mjd": 58730.4250116,
        "passband": 2,
        "mag": 19.503,
        "mag_err": 0.10305399999999999,
        "locus_id": "ZTF19abvhkst"
    },
    "5": {
        "mjd": 58730.475914400005,
        "passband": 1,
        "mag": 19.2837,
        "mag_err": 0.13481600000000002,
        "locus_id": "ZTF19abvhkst"
    },
    "6": {
        "mjd": 58733.4088079,
        "passband": 2,
        "mag": 18.8114,
        "mag_err": 0.0799802,
        "locus_id": "ZTF19abvhkst"
    },
    "7": {
        "mjd": 58733.40927080001,
        "passband": 2,
        "mag": 18.8656,
        "mag_err": 0.0638323,
        "locus_id": "ZTF19abvhkst"
    },
    "8": {
        "mjd": 58733.4440625,
        "passband": 1,
        "mag": 18.7167,
        "mag_err": 0.110447,
        "locus_id": "ZTF19abvhkst"
    },
    "9": {
        "mjd": 58733.44451390001,
        "passband": 1,
        "mag": 18.6402,
        "mag_err": 0.0750762,
        "locus_id": "ZTF19abvhkst"
    },
    "10": {
        "mjd": 58736.4297569,
        "passband": 2,
        "mag": 18.5231,
        "mag_err": 0.0770362,
        "locus_id": "ZTF19abvhkst"
    },
    "11": {
        "mjd": 58736.43020830001,
        "passband": 2,
        "mag": 18.5023,
        "mag_err": 0.04396,
        "locus_id": "ZTF19abvhkst"
    },
    "12": {
        "mjd": 58736.462928199995,
        "passband": 1,
        "mag": 18.3923,
        "mag_err": 0.0747043,
        "locus_id": "ZTF19abvhkst"
    },
    "13": {
        "mjd": 58736.46339119999,
        "passband": 1,
        "mag": 18.3783,
        "mag_err": 0.0667693,
        "locus_id": "ZTF19abvhkst"
    },
    "14": {
        "mjd": 58739.3807755,
        "passband": 2,
        "mag": 18.3937,
        "mag_err": 0.07637519999999999,
        "locus_id": "ZTF19abvhkst"
    },
    "15": {
        "mjd": 58739.401481500005,
        "passband": 2,
        "mag": 18.3404,
        "mag_err": 0.0897352,
        "locus_id": "ZTF19abvhkst"
    },
    "16": {
        "mjd": 58739.4875,
        "passband": 1,
        "mag": 18.2319,
        "mag_err": 0.0826452,
        "locus_id": "ZTF19abvhkst"
    },
    "17": {
        "mjd": 58739.51675930001,
        "passband": 1,
        "mag": 18.2693,
        "mag_err": 0.0909423,
        "locus_id": "ZTF19abvhkst"
    },
    "18": {
        "mjd": 58743.35782409999,
        "passband": 2,
        "mag": 18.3382,
        "mag_err": 0.07530099999999999,
        "locus_id": "ZTF19abvhkst"
    },
    "19": {
        "mjd": 58743.358287,
        "passband": 2,
        "mag": 18.3121,
        "mag_err": 0.101091,
        "locus_id": "ZTF19abvhkst"
    },
    "20": {
        "mjd": 58743.401481500005,
        "passband": 1,
        "mag": 18.1079,
        "mag_err": 0.077898,
        "locus_id": "ZTF19abvhkst"
    },
    "21": {
        "mjd": 58743.4019444,
        "passband": 1,
        "mag": 18.2302,
        "mag_err": 0.087464,
        "locus_id": "ZTF19abvhkst"
    },
    "22": {
        "mjd": 58746.3823611,
        "passband": 1,
        "mag": 18.2613,
        "mag_err": 0.077974,
        "locus_id": "ZTF19abvhkst"
    },
    "23": {
        "mjd": 58746.39039349999,
        "passband": 1,
        "mag": 18.3349,
        "mag_err": 0.0750928,
        "locus_id": "ZTF19abvhkst"
    },
    "24": {
        "mjd": 58749.298981500004,
        "passband": 2,
        "mag": 18.448,
        "mag_err": 0.057986,
        "locus_id": "ZTF19abvhkst"
    },
    "25": {
        "mjd": 58749.2994444,
        "passband": 2,
        "mag": 18.4952,
        "mag_err": 0.07349989999999999,
        "locus_id": "ZTF19abvhkst"
    },
    "26": {
        "mjd": 58749.3241898,
        "passband": 1,
        "mag": 18.4028,
        "mag_err": 0.0736806,
        "locus_id": "ZTF19abvhkst"
    },
    "27": {
        "mjd": 58749.3246528,
        "passband": 1,
        "mag": 18.4423,
        "mag_err": 0.0760581,
        "locus_id": "ZTF19abvhkst"
    },
    "28": {
        "mjd": 58757.3317593,
        "passband": 2,
        "mag": 18.945999999999998,
        "mag_err": 0.0579476,
        "locus_id": "ZTF19abvhkst"
    },
    "29": {
        "mjd": 58757.3322222,
        "passband": 2,
        "mag": 18.9478,
        "mag_err": 0.0954552,
        "locus_id": "ZTF19abvhkst"
    },
    "30": {
        "mjd": 58757.4103125,
        "passband": 1,
        "mag": 19.0763,
        "mag_err": 0.123627,
        "locus_id": "ZTF19abvhkst"
    },
    "31": {
        "mjd": 58757.41076390001,
        "passband": 1,
        "mag": 19.0716,
        "mag_err": 0.119505,
        "locus_id": "ZTF19abvhkst"
    },
    "32": {
        "mjd": 58760.326516199995,
        "passband": 2,
        "mag": 19.0734,
        "mag_err": 0.12946300000000002,
        "locus_id": "ZTF19abvhkst"
    },
    "33": {
        "mjd": 58760.32697919999,
        "passband": 2,
        "mag": 19.0394,
        "mag_err": 0.060028899999999996,
        "locus_id": "ZTF19abvhkst"
    },
    "34": {
        "mjd": 58760.371736099994,
        "passband": 1,
        "mag": 19.2339,
        "mag_err": 0.11818,
        "locus_id": "ZTF19abvhkst"
    },
    "35": {
        "mjd": 58760.37219909999,
        "passband": 1,
        "mag": 19.31,
        "mag_err": 0.108821,
        "locus_id": "ZTF19abvhkst"
    },
    "36": {
        "mjd": 58763.336817100004,
        "passband": 2,
        "mag": 19.1354,
        "mag_err": 0.09495239999999999,
        "locus_id": "ZTF19abvhkst"
    },
    "37": {
        "mjd": 58763.349375,
        "passband": 2,
        "mag": 19.0757,
        "mag_err": 0.069485,
        "locus_id": "ZTF19abvhkst"
    },
    "38": {
        "mjd": 58763.39173609999,
        "passband": 1,
        "mag": 19.5631,
        "mag_err": 0.148155,
        "locus_id": "ZTF19abvhkst"
    },
    "39": {
        "mjd": 58763.392199099995,
        "passband": 1,
        "mag": 19.5782,
        "mag_err": 0.147726,
        "locus_id": "ZTF19abvhkst"
    },
    "40": {
        "mjd": 58764.132650499996,
        "passband": 2,
        "mag": 19.0623,
        "mag_err": 0.108168,
        "locus_id": "ZTF19abvhkst"
    },
    "41": {
        "mjd": 58764.135046300005,
        "passband": 2,
        "mag": 19.1312,
        "mag_err": 0.129909,
        "locus_id": "ZTF19abvhkst"
    },
    "42": {
        "mjd": 58764.16550930001,
        "passband": 1,
        "mag": 19.7023,
        "mag_err": 0.221548,
        "locus_id": "ZTF19abvhkst"
    },
    "43": {
        "mjd": 58764.1684028,
        "passband": 1,
        "mag": 19.885,
        "mag_err": 0.25467199999999995,
        "locus_id": "ZTF19abvhkst"
    },
    "44": {
        "mjd": 58765.132835599994,
        "passband": 2,
        "mag": 19.1301,
        "mag_err": 0.12364000000000001,
        "locus_id": "ZTF19abvhkst"
    },
    "45": {
        "mjd": 58765.1352431,
        "passband": 2,
        "mag": 19.1878,
        "mag_err": 0.182201,
        "locus_id": "ZTF19abvhkst"
    },
    "46": {
        "mjd": 58765.1663079,
        "passband": 1,
        "mag": 19.6138,
        "mag_err": 0.264069,
        "locus_id": "ZTF19abvhkst"
    },
    "47": {
        "mjd": 58765.169213,
        "passband": 1,
        "mag": 19.6629,
        "mag_err": 0.205808,
        "locus_id": "ZTF19abvhkst"
    },
    "48": {
        "mjd": 58766.13258099999,
        "passband": 2,
        "mag": 19.2712,
        "mag_err": 0.21285,
        "locus_id": "ZTF19abvhkst"
    },
    "49": {
        "mjd": 58766.135463,
        "passband": 2,
        "mag": 19.1423,
        "mag_err": 0.18720599999999998,
        "locus_id": "ZTF19abvhkst"
    },
    "50": {
        "mjd": 58766.16486109999,
        "passband": 1,
        "mag": 19.7256,
        "mag_err": 0.298097,
        "locus_id": "ZTF19abvhkst"
    },
    "51": {
        "mjd": 58766.16776619999,
        "passband": 1,
        "mag": 19.7688,
        "mag_err": 0.33770700000000003,
        "locus_id": "ZTF19abvhkst"
    },
    "52": {
        "mjd": 58767.1327662,
        "passband": 2,
        "mag": 19.053,
        "mag_err": 0.265708,
        "locus_id": "ZTF19abvhkst"
    },
    "53": {
        "mjd": 58768.132974500004,
        "passband": 2,
        "mag": 19.1534,
        "mag_err": 0.180841,
        "locus_id": "ZTF19abvhkst"
    },
    "54": {
        "mjd": 58768.135856500005,
        "passband": 2,
        "mag": 19.0988,
        "mag_err": 0.176399,
        "locus_id": "ZTF19abvhkst"
    },
    "55": {
        "mjd": 58769.1354051,
        "passband": 2,
        "mag": 18.9082,
        "mag_err": 0.14720999999999998,
        "locus_id": "ZTF19abvhkst"
    },
    "56": {
        "mjd": 58771.1364583,
        "passband": 2,
        "mag": 19.1951,
        "mag_err": 0.242273,
        "locus_id": "ZTF19abvhkst"
    },
    "57": {
        "mjd": 58772.133761599995,
        "passband": 2,
        "mag": 19.2123,
        "mag_err": 0.173208,
        "locus_id": "ZTF19abvhkst"
    },
    "58": {
        "mjd": 58772.136643499995,
        "passband": 2,
        "mag": 19.3682,
        "mag_err": 0.199782,
        "locus_id": "ZTF19abvhkst"
    },
    "59": {
        "mjd": 58773.133669,
        "passband": 2,
        "mag": 19.3725,
        "mag_err": 0.179588,
        "locus_id": "ZTF19abvhkst"
    },
    "60": {
        "mjd": 58773.1365625,
        "passband": 2,
        "mag": 19.3166,
        "mag_err": 0.170309,
        "locus_id": "ZTF19abvhkst"
    },
    "61": {
        "mjd": 58774.1339699,
        "passband": 2,
        "mag": 19.3412,
        "mag_err": 0.17618399999999998,
        "locus_id": "ZTF19abvhkst"
    },
    "62": {
        "mjd": 58774.1368519,
        "passband": 2,
        "mag": 19.2762,
        "mag_err": 0.151892,
        "locus_id": "ZTF19abvhkst"
    },
    "63": {
        "mjd": 58774.16498840001,
        "passband": 1,
        "mag": 20.2467,
        "mag_err": 0.274547,
        "locus_id": "ZTF19abvhkst"
    },
    "64": {
        "mjd": 58775.133692100004,
        "passband": 2,
        "mag": 19.5115,
        "mag_err": 0.110799,
        "locus_id": "ZTF19abvhkst"
    },
    "65": {
        "mjd": 58775.1365856,
        "passband": 2,
        "mag": 19.4102,
        "mag_err": 0.138933,
        "locus_id": "ZTF19abvhkst"
    },
    "66": {
        "mjd": 58775.1650926,
        "passband": 1,
        "mag": 20.644000000000002,
        "mag_err": 0.30221,
        "locus_id": "ZTF19abvhkst"
    },
    "67": {
        "mjd": 58776.133483800004,
        "passband": 2,
        "mag": 19.547,
        "mag_err": 0.14216800000000002,
        "locus_id": "ZTF19abvhkst"
    },
    "68": {
        "mjd": 58776.1363773,
        "passband": 2,
        "mag": 19.505,
        "mag_err": 0.174369,
        "locus_id": "ZTF19abvhkst"
    },
    "69": {
        "mjd": 58776.16138890001,
        "passband": 1,
        "mag": 20.4574,
        "mag_err": 0.301385,
        "locus_id": "ZTF19abvhkst"
    },
    "70": {
        "mjd": 58776.1643287,
        "passband": 1,
        "mag": 20.4881,
        "mag_err": 0.275407,
        "locus_id": "ZTF19abvhkst"
    },
    "71": {
        "mjd": 58777.1338889,
        "passband": 2,
        "mag": 19.5476,
        "mag_err": 0.14745,
        "locus_id": "ZTF19abvhkst"
    },
    "72": {
        "mjd": 58777.136794000005,
        "passband": 2,
        "mag": 19.5702,
        "mag_err": 0.172492,
        "locus_id": "ZTF19abvhkst"
    },
    "73": {
        "mjd": 58777.16476849999,
        "passband": 1,
        "mag": 20.0617,
        "mag_err": 0.30795,
        "locus_id": "ZTF19abvhkst"
    },
    "74": {
        "mjd": 58778.134074099995,
        "passband": 2,
        "mag": 19.8353,
        "mag_err": 0.146199,
        "locus_id": "ZTF19abvhkst"
    },
    "75": {
        "mjd": 58778.1369792,
        "passband": 2,
        "mag": 19.583,
        "mag_err": 0.163026,
        "locus_id": "ZTF19abvhkst"
    },
    "76": {
        "mjd": 58778.1649653,
        "passband": 1,
        "mag": 20.5705,
        "mag_err": 0.250309,
        "locus_id": "ZTF19abvhkst"
    },
    "77": {
        "mjd": 58779.1338773,
        "passband": 2,
        "mag": 19.7214,
        "mag_err": 0.196104,
        "locus_id": "ZTF19abvhkst"
    },
    "78": {
        "mjd": 58779.1367824,
        "passband": 2,
        "mag": 19.6294,
        "mag_err": 0.190104,
        "locus_id": "ZTF19abvhkst"
    },
    "79": {
        "mjd": 58781.1366898,
        "passband": 2,
        "mag": 19.8888,
        "mag_err": 0.24654,
        "locus_id": "ZTF19abvhkst"
    },
    "80": {
        "mjd": 58782.1328704,
        "passband": 2,
        "mag": 19.834,
        "mag_err": 0.197516,
        "locus_id": "ZTF19abvhkst"
    },
    "81": {
        "mjd": 58783.1370023,
        "passband": 2,
        "mag": 19.8995,
        "mag_err": 0.21050100000000002,
        "locus_id": "ZTF19abvhkst"
    }
}