{
    "0": {
        "mjd": 58633.1690278,
        "passband": 2,
        "mag": 17.8812,
        "mag_err": 0.07629810000000001,
        "locus_id": "ZTF19aavqics"
    },
    "1": {
        "mjd": 58633.2281944,
        "passband": 1,
        "mag": 17.7308,
        "mag_err": 0.0552794,
        "locus_id": "ZTF19aavqics"
    },
    "2": {
        "mjd": 58636.2455324,
        "passband": 1,
        "mag": 17.3506,
        "mag_err": 0.0468571,
        "locus_id": "ZTF19aavqics"
    },
    "3": {
        "mjd": 58639.178125,
        "passband": 2,
        "mag": 17.0082,
        "mag_err": 0.048869,
        "locus_id": "ZTF19aavqics"
    },
    "4": {
        "mjd": 58639.2263889,
        "passband": 1,
        "mag": 16.9125,
        "mag_err": 0.045001599999999996,
        "locus_id": "ZTF19aavqics"
    },
    "5": {
        "mjd": 58642.1992593,
        "passband": 1,
        "mag": 16.8383,
        "mag_err": 0.0418857,
        "locus_id": "ZTF19aavqics"
    },
    "6": {
        "mjd": 58642.2146644,
        "passband": 2,
        "mag": 16.8981,
        "mag_err": 0.039454199999999995,
        "locus_id": "ZTF19aavqics"
    },
    "7": {
        "mjd": 58646.1714699,
        "passband": 1,
        "mag": 16.8737,
        "mag_err": 0.15115399999999998,
        "locus_id": "ZTF19aavqics"
    },
    "8": {
        "mjd": 58646.2134375,
        "passband": 2,
        "mag": 16.8074,
        "mag_err": 0.0483815,
        "locus_id": "ZTF19aavqics"
    },
    "9": {
        "mjd": 58649.17530090001,
        "passband": 1,
        "mag": 16.8927,
        "mag_err": 0.0527775,
        "locus_id": "ZTF19aavqics"
    },
    "10": {
        "mjd": 58649.2184722,
        "passband": 2,
        "mag": 16.8857,
        "mag_err": 0.0383605,
        "locus_id": "ZTF19aavqics"
    },
    "11": {
        "mjd": 58653.187523099994,
        "passband": 2,
        "mag": 17.2441,
        "mag_err": 0.0554024,
        "locus_id": "ZTF19aavqics"
    },
    "12": {
        "mjd": 58653.2566551,
        "passband": 1,
        "mag": 17.3815,
        "mag_err": 0.06585650000000001,
        "locus_id": "ZTF19aavqics"
    },
    "13": {
        "mjd": 58658.1813426,
        "passband": 2,
        "mag": 17.7752,
        "mag_err": 0.0668581,
        "locus_id": "ZTF19aavqics"
    },
    "14": {
        "mjd": 58658.193738400005,
        "passband": 1,
        "mag": 18.0583,
        "mag_err": 0.0654925,
        "locus_id": "ZTF19aavqics"
    },
    "15": {
        "mjd": 58662.177372699996,
        "passband": 2,
        "mag": 18.14,
        "mag_err": 0.09527689999999998,
        "locus_id": "ZTF19aavqics"
    },
    "16": {
        "mjd": 58662.200173599995,
        "passband": 1,
        "mag": 18.4656,
        "mag_err": 0.08916519999999999,
        "locus_id": "ZTF19aavqics"
    },
    "17": {
        "mjd": 58668.1927546,
        "passband": 1,
        "mag": 18.8273,
        "mag_err": 0.1166,
        "locus_id": "ZTF19aavqics"
    },
    "18": {
        "mjd": 58673.2080671,
        "passband": 2,
        "mag": 18.4112,
        "mag_err": 0.08053889999999998,
        "locus_id": "ZTF19aavqics"
    },
    "19": {
        "mjd": 58676.1758796,
        "passband": 1,
        "mag": 18.8766,
        "mag_err": 0.17222,
        "locus_id": "ZTF19aavqics"
    },
    "20": {
        "mjd": 58676.1960764,
        "passband": 2,
        "mag": 18.3934,
        "mag_err": 0.116869,
        "locus_id": "ZTF19aavqics"
    },
    "21": {
        "mjd": 58679.201516199995,
        "passband": 2,
        "mag": 18.38,
        "mag_err": 0.0891378,
        "locus_id": "ZTF19aavqics"
    }
}